acasclient/CmpdReg.py
acasclient/StereoCategory.py
acasclient/__init__.py
acasclient/acasclient.py
acasclient/cli.py
acasclient/ddict.py
acasclient/experiment.py
acasclient/interactions.py
acasclient/lsthing.py
acasclient/protocol.py
acasclient/selfile.py
acasclient/validation.py
acasclient-2026.1.0.dist-info/AUTHORS.rst
acasclient-2026.1.0.dist-info/LICENSE
acasclient-2026.1.0.dist-info/METADATA
acasclient-2026.1.0.dist-info/WHEEL
acasclient-2026.1.0.dist-info/entry_points.txt
acasclient-2026.1.0.dist-info/top_level.txt
acasclient-2026.1.0.dist-info/RECORD
