Metadata-Version: 2.1
Name: acasclient
Version: 2026.1.0
Summary: ACAS API Client
Home-page: https://github.com/mcneilco/acasclient
Author: Brian Bolt
Author-email: brian.bolt@boltengineered.com
License: GNU General Public License v3
Keywords: acasclient
Classifier: Development Status :: 2 - Pre-Alpha
Classifier: Intended Audience :: Developers
Classifier: License :: OSI Approved :: GNU General Public License v3 (GPLv3)
Classifier: Natural Language :: English
Classifier: Programming Language :: Python :: 3
Classifier: Programming Language :: Python :: 3.5
Classifier: Programming Language :: Python :: 3.6
Classifier: Programming Language :: Python :: 3.7
Classifier: Programming Language :: Python :: 3.8
Requires-Python: >=3.5
License-File: LICENSE
License-File: AUTHORS.rst
Requires-Dist: requests
Requires-Dist: pandas
Requires-Dist: six
Requires-Dist: decorator
Requires-Dist: openpyxl
Requires-Dist: xlrd
